bin/__init__.py
bin/ecsopera.py
ecsopera/__init__.py
ecsopera/asciistr.py
ecsopera/awsamiupdate.py
ecsopera/awscommands.py
ecsopera/awsecsdeploy.py
ecsopera/awss3cpdeploy.py
ecsopera/cli.py
ecsopera/loghelper.py
ecsopera/raiseexception.py
ecsopera/version.py
ecsopera-0.0.7.dist-info/METADATA
ecsopera-0.0.7.dist-info/RECORD
ecsopera-0.0.7.dist-info/WHEEL
ecsopera-0.0.7.dist-info/entry_points.txt
ecsopera-0.0.7.dist-info/top_level.txt
