Metadata-Version: 2.1
Name: ecsopera
Version: 0.0.7
Summary: Elastic Container Orchestrator Toolset.
Home-page: http://github.com/Pashbee/ecsopera
Author: Pashbee
Author-email: UNKNOWN
License: MIT
Platform: UNKNOWN
Classifier: Environment :: Console
Classifier: Intended Audience :: Developers
Classifier: License :: OSI Approved :: MIT License
Classifier: Operating System :: POSIX
Classifier: Operating System :: MacOS
Classifier: Operating System :: Unix
Classifier: Programming Language :: Python
Classifier: Programming Language :: Python :: 3
Classifier: Topic :: Software Development :: Libraries :: Python Modules
Requires-Dist: click
Requires-Dist: boto3
Requires-Dist: moto
Requires-Dist: progressbar2
Requires-Dist: pytest
